{
    "label_id":  "FUN_11",
    "title":  "Czubajka kania",
    "description":  "Czubajka kania (Macrolepiota procera (Scop.) Singer) – gatunek grzybów należący do rodziny pieczarkowatych (Agaricaceae).",
    "source_url":  "https://pl.wikipedia.org/wiki/Czubajka_kania",
    "image_file":  "FUN_11-dataset.jpg",
    "image_url":  "https://upload.wikimedia.org/wikipedia/commons/thumb/a/a4/Macrolepiota-procera.jpg/960px-Macrolepiota-procera.jpg",
    "search_query":  "Macrolepiota procera",
    "downloaded_at":  "2026-05-20T20:50:25.0930440Z",
    "dataset_image_source":  "D:\\NaturaVisionPortable\\portable_dataset\\images\\FUN_11\\438899689.jpg"
}
